# pydisasm version 6.0.5
# Python bytecode 3.8.0 (3413)
# Disassembled from Python 3.8.17 (default, Jul  4 2023, 06:27:59) 
# [GCC 12.2.0]
# Timestamp in code: 1691495825 (2023-08-08 11:57:05)
# Source code size mod 2**32: 269 bytes
# Method Name:       <module>
# Filename:          1.py
# Argument count:    0
# Position-only argument count: 0
# Keyword-only arguments: 0
# Number of locals:  0
# Stack size:        4
# Flags:             0x00000040 (NOFREE)
# First Line:        2
# Constants:
#    0: <code object BBB at 0x7f3b403b9240, file "1.py", line 2>
#    1: 'BBB'
#    2: 1
#    3: 2
#    4: 3
#    5: None
# Names:
#    0: BBB
  2:           0 LOAD_CONST           (<code object BBB at 0x7f3b403b9240, file "1.py", line 2>)
               2 LOAD_CONST           ('BBB')
               4 MAKE_FUNCTION        (Neither defaults, keyword-only args, annotations, nor closures)
               6 STORE_NAME           (BBB)

 24:           8 LOAD_NAME            (BBB)
              10 LOAD_CONST           (1)
              12 LOAD_CONST           (2)
              14 LOAD_CONST           (3)
              16 CALL_FUNCTION        3
              18 POP_TOP
              20 LOAD_CONST           (None)
              22 RETURN_VALUE


# Method Name:       BBB
# Filename:          1.py
# Argument count:    3
# Position-only argument count: 0
# Keyword-only arguments: 0
# Number of locals:  5
# Stack size:        3
# Flags:             0x00000043 (NOFREE | NEWLOCALS | OPTIMIZED)
# First Line:        2
# Constants:
#    0: None
#    1: 10
#    2: 5
#    3: 1
#    4: 3
#    5: 100
#    6: 0
# Names:
#    0: print
#    1: range
#    2: quit
# Varnames:
#	a, s, b, c, i
# Positional arguments:
#	a, s, b
# Local variables:
#    3: c
#    4: i
  3:           0 LOAD_CONST           (10)
               2 STORE_FAST           (a)

  4:           4 LOAD_FAST            (a)
               6 LOAD_CONST           (5)
               8 BINARY_SUBTRACT
              10 STORE_FAST           (a)

  5:          12 LOAD_FAST            (a)
              14 LOAD_CONST           (5)
              16 BINARY_MULTIPLY
              18 STORE_FAST           (a)

  6:          20 LOAD_GLOBAL          (print)
              22 LOAD_FAST            (a)
              24 CALL_FUNCTION        1
              26 POP_TOP

  8:          28 LOAD_CONST           (1)
              30 STORE_FAST           (a)

  9:          32 LOAD_CONST           (3)
              34 STORE_FAST           (c)

 10:          36 LOAD_GLOBAL          (range)
              38 LOAD_CONST           (10)
              40 CALL_FUNCTION        1
              42 GET_ITER
         >>   44 FOR_ITER             (to 58)
              46 STORE_FAST           (i)

 11:          48 LOAD_FAST            (a)
              50 LOAD_FAST            (i)
              52 INPLACE_ADD
              54 STORE_FAST           (a)
              56 JUMP_ABSOLUTE        (to 44)

 13:     >>   58 LOAD_FAST            (b)
              60 LOAD_CONST           (100)
              62 COMPARE_OP           (<)
              64 POP_JUMP_IF_FALSE    (to 84)

 14:          66 LOAD_FAST            (b)
              68 LOAD_CONST           (1)
              70 INPLACE_ADD
              72 STORE_FAST           (b)

 15:          74 LOAD_FAST            (a)
              76 LOAD_FAST            (b)
              78 INPLACE_ADD
              80 STORE_FAST           (a)
              82 JUMP_ABSOLUTE        (to 58)

 16:     >>   84 LOAD_FAST            (a)
              86 LOAD_CONST           (0)
              88 COMPARE_OP           (>=)
              90 POP_JUMP_IF_FALSE    (to 108)
              92 LOAD_FAST            (c)
              94 LOAD_CONST           (3)
              96 COMPARE_OP           (==)
              98 POP_JUMP_IF_FALSE    (to 108)

 17:         100 LOAD_FAST            (a)
             102 STORE_FAST           (b)

 18:         104 LOAD_CONST           (None)
             106 RETURN_VALUE

 20:     >>  108 LOAD_FAST            (a)
             110 UNARY_NEGATIVE
             112 STORE_FAST           (b)

 21:         114 LOAD_GLOBAL          (quit)
             116 CALL_FUNCTION        0
             118 POP_TOP

 22:         120 LOAD_CONST           (None)
             122 RETURN_VALUE

